
  {
    "power": 
      {
        "switch": true
      }
    ,

    "data": [


        {
        "title": "Open",
        "imageurl": "https://raw.githubusercontent.com/jfresh194/indigosl/refs/heads/main/Media31545__200%D1%85200_af.gif",
        "link": "https://refpa3740576.top/C?tag=d_3124209m_31547c_&site=3124209&ad=31547&urlred=https%3A%2F%2F1xbet.sl%2Fen",
        "colorleft": "#fff88f",
        "colorright": "#ffffff",
        "buttonTitle": "Open",
        "buttonBgColor": "#25f8ff",
        "buttonTitleColor": "#000fff",
        "countryToShow": "EN",
        "rewardDisplaytime": 5
      }

      
    ]
  }
